ram/__init__.py
ram/__main__.py
ram/config.py
ram/modules.py
ram/plot.py
ram/ram.py
ram/tester.py
ram/trainer.py
ram/dataset/__init__.py
ram/dataset/data.py
ram/dataset/mnist.py
thrillington-0.0.2a1.dist-info/LICENSE
thrillington-0.0.2a1.dist-info/METADATA
thrillington-0.0.2a1.dist-info/WHEEL
thrillington-0.0.2a1.dist-info/entry_points.txt
thrillington-0.0.2a1.dist-info/top_level.txt
thrillington-0.0.2a1.dist-info/RECORD
