Metadata-Version: 2.1
Name: thrillington
Version: 0.0.2a1
Summary: Replication of "Recurrent models of visual attention", Mnih et al. 2014
Home-page: https://github.com/NickleDave/thrillington
Author: Percy "Thrills" Thrillington
Author-email: nicholdav@gmail.com
License: BSD
Platform: UNKNOWN
Classifier: License :: OSI Approved :: BSD License
Classifier: Programming Language :: Python
Classifier: Programming Language :: Python :: 3
Classifier: Programming Language :: Python :: 3.6
Classifier: Programming Language :: Python :: Implementation :: CPython
Requires-Python: >=3.6.0
Requires-Dist: numpy
Requires-Dist: tensorflow
Requires-Dist: tqdm
Requires-Dist: attrs
